hdex/__init__.py
hdex-0.20.10.31.10.dist-info/LICENSE
hdex-0.20.10.31.10.dist-info/METADATA
hdex-0.20.10.31.10.dist-info/WHEEL
hdex-0.20.10.31.10.dist-info/top_level.txt
hdex-0.20.10.31.10.dist-info/RECORD
