Metadata-Version: 2.1
Name: hdex
Version: 0.20.10.31.10
Summary: It will genarate dictionary for your keywords
Home-page: UNKNOWN
Author: harsh pratap bhardwaj
Author-email: harshpratap652@gmail.com
License: MIT
Platform: UNKNOWN
